pyramid_localize/__init__.py
pyramid_localize/models.py
pyramid_localize/negotiator.py
pyramid_localize/request.py
pyramid_localize/tools.py
pyramid_localize/routing/__init__.py
pyramid_localize/routing/predicates.py
pyramid_localize/subscribers/__init__.py
pyramid_localize/subscribers/fake.py
pyramid_localize/subscribers/i18n.py
pyramid_localize/views/__init__.py
pyramid_localize/views/catalogue.py
pyramid_localize-1.0.7.dist-info/AUTHORS.rst
pyramid_localize-1.0.7.dist-info/LICENSE
pyramid_localize-1.0.7.dist-info/METADATA
pyramid_localize-1.0.7.dist-info/WHEEL
pyramid_localize-1.0.7.dist-info/top_level.txt
pyramid_localize-1.0.7.dist-info/zip-safe
pyramid_localize-1.0.7.dist-info/RECORD
