Metadata-Version: 2.1
Name: pyramid_localize
Version: 1.0.7
Summary: pyramid_localize provides translation methods for pyramid, and means to reload translations without stopping the application
Author-email: Grzegorz Śliwiński <fizyk+pypi@fizyk.dev>
License: The MIT License (MIT): http://opensource.org/licenses/MIT
Project-URL: Source, https://github.com/fizyk/pyramid_localize/
Project-URL: Bug Tracker, https://github.com/fizyk/pyramid_localize/issues
Project-URL: Changelog, https://github.com/fizyk/pyramid_localize/blob/v1.0.7/CHANGES.rst
Keywords: pyramid,babel,i18n,l10n
Classifier: Development Status :: 5 - Production/Stable
Classifier: Environment :: Web Environment
Classifier: Intended Audience :: Developers
Classifier: License :: OSI Approved :: MIT License
Classifier: Natural Language :: English
Classifier: Operating System :: OS Independent
Classifier: Programming Language :: Python
Classifier: Programming Language :: Python :: 3
Classifier: Programming Language :: Python :: 3.9
Classifier: Programming Language :: Python :: 3.10
Classifier: Programming Language :: Python :: 3.11
Classifier: Programming Language :: Python :: 3.12
Classifier: Programming Language :: Python :: 3.13
Classifier: Framework :: Pyramid
Classifier: Topic :: Database :: Front-Ends
Classifier: Topic :: Internet :: WWW/HTTP
Classifier: Topic :: Internet :: WWW/HTTP :: WSGI
Classifier: Topic :: Software Development :: Libraries :: Python Modules
Requires-Python: >=3.9
License-File: LICENSE
License-File: AUTHORS.rst
Requires-Dist: pyramid>=1.5
Requires-Dist: pyramid-basemodel
Requires-Dist: pyramid-mako
Requires-Dist: pycountry>=23.12.7
Provides-Extra: babel
Requires-Dist: Babel>=1.0; extra == "babel"
Provides-Extra: docs
Requires-Dist: sphinx; extra == "docs"
